[
  {
    "id": "product4",
    "name": "gooday",
    "slug": "gooday",
    "description": "gooday kopi yang buat hari good.",
    "image": {
      "id": 1,
      "thumbnail": "/assets/images/products/gooday.jpg",
      "original": "/assets/images/products/gooday.jpg"
    },
    "gallery": [
      {
        "id": 1,
        "thumbnail": "/assets/images/products/gooday.jpg",
        "original": "/assets/images/products/gooday.jpg"
      }
    ],
    "quantity": 70,
    "price": 2.74,
    "sale_price": 2.64,
    "unit": "1 each",
    "tag": [
      {
        "id": 1,
        "name": "Fresh food",
        "slug": "fresh-food"
      },
      {
        "id": 2,
        "name": "Organic",
        "slug": "organic"
      },
      {
        "id": 3,
        "name": "Cilantro",
        "slug": "cilantro"
      },
      {
        "id": 4,
        "name": "Dry Food",
        "slug": "dry-food"
      }
    ]
  },

  {
    "id": "product6",
    "name": "indomie goreng",
    "slug": "indomi",
    "description": "indomie goreng.",
    "image": {
      "id": 1,
      "thumbnail": "/assets/images/products/indomi.jpg",
      "original": "/assets/images/products/indomi.jpg"
    },
    "gallery": [
      {
        "id": 1,
        "thumbnail": "/assets/images/products/indomi.jpg",
        "original": "/assets/images/products/indomi.jpg"
      }
    ],
    "quantity": 70,
    "price": 2.74,
    "sale_price": 2.64,
    "unit": "1 each",
    "tag": [
      {
        "id": 1,
        "name": "Fresh food",
        "slug": "fresh-food"
      },
      {
        "id": 2,
        "name": "Organic",
        "slug": "organic"
      },
      {
        "id": 3,
        "name": "Cilantro",
        "slug": "cilantro"
      },
      {
        "id": 4,
        "name": "Dry Food",
        "slug": "dry-food"
      }
    ]
  },
  

  {
    "id": "product7",
    "name": "indomie rendang",
    "slug": "indomie_rendang",
    "description": "indomie rendang sensasi masakan padang.",
    "image": {
      "id": 1,
      "thumbnail": "/assets/images/products/indomie_rendang.jpg",
      "original": "/assets/images/products/indomie_rendang.jpg"
    },
    "gallery": [
      {
        "id": 1,
        "thumbnail": "/assets/images/products/indomie_rendang.jpg",
        "original": "/assets/images/products/indomie_rendang.jpg"
      }
    ],
    "quantity": 70,
    "price": 2.74,
    "sale_price": 2.64,
    "unit": "1 each",
    "tag": [
      {
        "id": 1,
        "name": "Fresh food",
        "slug": "fresh-food"
      },
      {
        "id": 2,
        "name": "Organic",
        "slug": "organic"
      },
      {
        "id": 3,
        "name": "Cilantro",
        "slug": "cilantro"
      },
      {
        "id": 4,
        "name": "Dry Food",
        "slug": "dry-food"
      }
    ]
  },
  

  {
    "id": "product8",
    "name": "kaos kaki",
    "slug": "kaoskaki",
    "description": "terbuat dari kain pilihan.",
    "image": {
      "id": 1,
      "thumbnail": "/assets/images/products/kaoskaki.jpg",
      "original": "/assets/images/products/kaoskaki.jpg"
    },
    "gallery": [
      {
        "id": 1,
        "thumbnail": "/assets/images/products/kaoskaki.jpg",
        "original": "/assets/images/products/kaoskaki.jpg"
      }
    ],
    "quantity": 70,
    "price": 2.74,
    "sale_price": 2.64,
    "unit": "1 each",
    "tag": [
      {
        "id": 1,
        "name": "Fresh food",
        "slug": "fresh-food"
      },
      {
        "id": 2,
        "name": "Organic",
        "slug": "organic"
      },
      {
        "id": 3,
        "name": "Cilantro",
        "slug": "cilantro"
      },
      {
        "id": 4,
        "name": "Dry Food",
        "slug": "dry-food"
      }
    ]
  },

  {
    "id": "product9",
    "name": "kaos kaki sekolah",
    "slug": "kaoskaki_sklh",
    "description": "kaos kaki dari kain pilihan.",
    "image": {
      "id": 1,
      "thumbnail": "/assets/images/products/kaoskaki_sklh.jpg",
      "original": "/assets/images/products/kaoskaki_sklh.jpg"
    },
    "gallery": [
      {
        "id": 1,
        "thumbnail": "/assets/images/products/kaoskaki_sklh.jpg",
        "original": "/assets/images/products/kaoskaki_sklh.jpg"
      }
    ],
    "quantity": 70,
    "price": 2.74,
    "sale_price": 2.64,
    "unit": "1 each",
    "tag": [
      {
        "id": 1,
        "name": "Fresh food",
        "slug": "fresh-food"
      },
      {
        "id": 2,
        "name": "Organic",
        "slug": "organic"
      },
      {
        "id": 3,
        "name": "Cilantro",
        "slug": "cilantro"
      },
      {
        "id": 4,
        "name": "Dry Food",
        "slug": "dry-food"
      }
    ]
  },
  

  {
    "id": "product10",
    "name": "kertas",
    "slug": "kertas",
    "description": "mengisi kekosongan bukumu.",
    "image": {
      "id": 1,
      "thumbnail": "/assets/images/products/kertas.jpg",
      "original": "/assets/images/products/kertas.jpg"
    },
    "gallery": [
      {
        "id": 1,
        "thumbnail": "/assets/images/products/kertas.jpg",
        "original": "/assets/images/products/kertas.jpg"
      }
    ],
    "quantity": 70,
    "price": 2.74,
    "sale_price": 2.64,
    "unit": "1 each",
    "tag": [
      {
        "id": 1,
        "name": "Fresh food",
        "slug": "fresh-food"
      },
      {
        "id": 2,
        "name": "Organic",
        "slug": "organic"
      },
      {
        "id": 3,
        "name": "Cilantro",
        "slug": "cilantro"
      },
      {
        "id": 4,
        "name": "Dry Food",
        "slug": "dry-food"
      }
    ]
  },

  {
    "id": "product11",
    "name": "kripik gethuk",
    "slug": "kripik_gethuk",
    "description": "kripiknya orang indonesia.",
    "image": {
      "id": 1,
      "thumbnail": "/assets/images/products/kripik_gethuk.jpg",
      "original": "/assets/images/products/kripik_gethuk.jpg"
    },
    "gallery": [
      {
        "id": 1,
        "thumbnail": "/assets/images/products/kripik_gethuk.jpg",
        "original": "/assets/images/products/kripik_gethuk.jpg"
      }
    ],
    "quantity": 70,
    "price": 2.74,
    "sale_price": 2.64,
    "unit": "1 each",
    "tag": [
      {
        "id": 1,
        "name": "Fresh food",
        "slug": "fresh-food"
      },
      {
        "id": 2,
        "name": "Organic",
        "slug": "organic"
      },
      {
        "id": 3,
        "name": "Cilantro",
        "slug": "cilantro"
      },
      {
        "id": 4,
        "name": "Dry Food",
        "slug": "dry-food"
      }
    ]
  },
  

  {
    "id": "product12",
    "name": "mama lemon",
    "slug": "mama_lemon",
    "description": "membersikan kotoran sampai kinclong.",
    "image": {
      "id": 1,
      "thumbnail": "/assets/images/products/mama_lemon.jpg",
      "original": "/assets/images/products/mama_lemon.jpg"
    },
    "gallery": [
      {
        "id": 1,
        "thumbnail": "/assets/images/products/mama_lemon.jpg",
        "original": "/assets/images/products/mama_lemon.jpg"
      }
    ],
    "quantity": 70,
    "price": 2.74,
    "sale_price": 2.64,
    "unit": "1 each",
    "tag": [
      {
        "id": 1,
        "name": "Fresh food",
        "slug": "fresh-food"
      },
      {
        "id": 2,
        "name": "Organic",
        "slug": "organic"
      },
      {
        "id": 3,
        "name": "Cilantro",
        "slug": "cilantro"
      },
      {
        "id": 4,
        "name": "Dry Food",
        "slug": "dry-food"
      }
    ]
  }
  
]